LICENSE
MANIFEST.in
README.rst
setup.py
zion/__init__.py
zion/main.py
zion.egg-info/PKG-INFO
zion.egg-info/SOURCES.txt
zion.egg-info/dependency_links.txt
zion.egg-info/entry_points.txt
zion.egg-info/top_level.txt