Metadata-Version: 1.1
Name: zion
Version: 0.0.1
Summary: vpn over dns
Home-page: https://github.com/clowwindy/zion
Author: clowwindy
Author-email: clowwindy42@gmail.com
License: MIT
Platform: UNKNOWN
Classifier: License :: OSI Approved :: MIT License
Classifier: Programming Language :: Python :: 2
Classifier: Programming Language :: Python :: 2.6
Classifier: Programming Language :: Python :: 2.7
Classifier: Topic :: Internet :: Proxy Servers
